rag_fact_checker/__init__.py
rag_fact_checker/default_config.json
rag_fact_checker/llm_triplet_validator.py
rag_fact_checker/prompt_bank.json
rag_fact_checker/data/__init__.py
rag_fact_checker/data/data_models.py
rag_fact_checker/model/__init__.py
rag_fact_checker/model/fact_checker/__init__.py
rag_fact_checker/model/fact_checker/batch_fact_checker.py
rag_fact_checker/model/fact_checker/fact_checker.py
rag_fact_checker/model/fact_checker/llm_fact_checker.py
rag_fact_checker/model/fact_checker/llm_multishot_fact_checker.py
rag_fact_checker/model/fact_checker/llm_multishot_split_fact_checker.py
rag_fact_checker/model/fact_checker/llm_split_fact_checker.py
rag_fact_checker/model/hallucination_data_generator/__init__.py
rag_fact_checker/model/hallucination_data_generator/answer_based_hallucination_data_generator.py
rag_fact_checker/model/hallucination_data_generator/hallucination_data_generator.py
rag_fact_checker/model/hallucination_data_generator/llm_hallucination_data_generator.py
rag_fact_checker/model/hallucination_data_generator/llm_multishot_hallucination_data_generator.py
rag_fact_checker/model/triplet_generator/__init__.py
rag_fact_checker/model/triplet_generator/batch_triplet_generator.py
rag_fact_checker/model/triplet_generator/llm_multishot_triplet_generator.py
rag_fact_checker/model/triplet_generator/llm_triplet_generator.py
rag_fact_checker/model/triplet_generator/triplet_generator.py
rag_fact_checker/pipeline/__init__.py
rag_fact_checker/pipeline/batch_processor.py
rag_fact_checker/pipeline/pipeline_base.py
rag_fact_checker/pipeline/pipeline_demonstration.py
rag_fact_checker/pipeline/pipeline_llm.py
rag_fact_checker/pipeline/pipeline_prompt.py
rag_fact_checker/pipeline/simple_batch_processor.py
rag_fact_checker/utils/__init__.py
rag_fact_checker/utils/utils.py
rag_fact_checker-0.1.5.dist-info/licenses/LICENSE
rag_fact_checker-0.1.5.dist-info/METADATA
rag_fact_checker-0.1.5.dist-info/WHEEL
rag_fact_checker-0.1.5.dist-info/top_level.txt
rag_fact_checker-0.1.5.dist-info/RECORD
