Metadata-Version: 2.4
Name: rag_fact_checker
Version: 0.1.5
Summary: Fact-checking system using large language models.
Author-email: Ilir Osmanaj <ilirosmanaj.94@gmail.com>, Adam Kovacs <kovacs@krlabs.eu>
License: MIT
Project-URL: Homepage, https://github.com/KRLabsOrg/RAGFactChecker
Project-URL: Repository, https://github.com/KRLabsOrg/RAGFactChecker
Project-URL: Issues, https://github.com/KRLabsOrg/RAGFactChecker/issues
Classifier: Programming Language :: Python :: 3
Classifier: License :: OSI Approved :: MIT License
Classifier: Operating System :: OS Independent
Classifier: Development Status :: 3 - Alpha
Classifier: Intended Audience :: Developers
Classifier: Intended Audience :: Science/Research
Classifier: Topic :: Scientific/Engineering :: Artificial Intelligence
Classifier: Topic :: Text Processing :: Linguistic
Requires-Python: >=3.11
License-File: LICENSE
Requires-Dist: easydict==1.13
Requires-Dist: openai>=1.54.4
Requires-Dist: python-dotenv==1.0.1
Provides-Extra: dev
Requires-Dist: pytest>=7.0; extra == "dev"
Requires-Dist: pytest-cov>=4.0; extra == "dev"
Requires-Dist: ruff>=0.1.0; extra == "dev"
Requires-Dist: mypy>=1.0; extra == "dev"
Dynamic: license-file
